<?xml version="1.0" encoding="UTF-8"?>
<nifty xmlns="http://nifty-gui.sourceforge.net/nifty-1.3.xsd" xmlns:xsi="http://www.w3.org/2001/XMLSchema-instance" xsi:schemaLocation="http://nifty-gui.sourceforge.net/nifty-1.3.xsd http://nifty-gui.sourceforge.net/nifty-1.3.xsd">
    <!-- +++++++++++++++++++++++++++++++++++++++ -->
    <!-- start screen -->
    <!-- +++++++++++++++++++++++++++++++++++++++ -->
    <useStyles filename="nifty-default-styles.xml" />
    <useStyles filename="Interface/Nifty/rctcstyle-basic.xml" />
    <useControls filename="nifty-default-controls.xml" />
    <screen id="start" controller="intopark.GUI.StartScreen">
        <layer id="background2" height="100%" width="100%" childLayout="center">
            <image filename="Interface/Nifty/Transparent.png"  width="100%" height="100%"></image>
        </layer>
        <layer id="layer" height="100%" width="100%" backgroundColor="#fff0" childLayout="absolute"visibleToMouse="true">
            <panel id="buttones"x="0"y="0"height="100%" width="100%" backgroundColor="#fff4" childLayout="absolute"visibleToMouse="true">
                <control id="alphatest" name="button" label="Start new game!" x="500"y="600"width="30%"height="3%"visibleToMouse="true">
                    <interact onClick="onLoadNewGameButton()"/>
                </control>
                <control id="loadtest" name="button" label="Load old game!" x="500"y="560"width="30%"height="3%"visibleToMouse="true">
                    <interact onClick="onLoadGameButton()"/>
                </control>
                <control id="settings" name="button" label="Settings" x="500"y="640"width="30%"height="3%"visibleToMouse="true">
                </control>
                <control id="alphatestmessage"name="label"  color="#ffff" text="PLEASE NOTE THAT THIS IS PRE-ALPHA!" x="5"y="36"/>
                <control id="Author"name="label" font="Interface/Fonts/Impact.fnt"text="Made by Arttu Siren" x="5"y="10" color="#f55f"/>
                <control id="Version"name="label" font="Interface/Fonts/Impact.fnt"text="Version 0.06A" x="150"y="10" color="#EBB9C2"/>
            </panel>
            <control id="newgamewindow" name="window"title=" "width="400"height="500"x="10"y="100"hideOnClose="true"closeable="true">
                <panel x="0"y="0"id="negamepanel"valign="top"align="left"height="100%" width="100%" backgroundColor="#C4F590" childLayout="absolute"visibleToMouse="true">
                    <panel x="1%"y="10"id="newgame1"valign="top"align="left"height="120" width="98%" backgroundColor="#8FBF5C" childLayout="absolute"visibleToMouse="true">
                        <control id="newgamename1"name="label" font="Interface/Fonts/Impact.fnt"text="Green Golly" x="5"y="5" color="#FF4D88"/>
                        <control id="newgamedesc11"name="label" font="Interface/Fonts/Impact.fnt"text="Small local field where you and " x="5"y="30"color="#960233"/>
                        <control id="newgamedesc12"name="label" font="Interface/Fonts/Impact.fnt"text="your park have just arrived!" x="5"y="55"color="#960233"/>
                        <interact onClick="startGametrue()"/>
                    </panel>
                    <panel x="1%"y="140"id="newgame2"valign="top"align="left"height="120" width="98%" backgroundColor="#8FBF5C" childLayout="absolute"visibleToMouse="true">
                        <control id="newgamename2"name="label" font="Interface/Fonts/Impact.fnt"text="Mighty Yral Mountains" x="5"y="5" color="#FF4D88"/>
                        <control id="newgamedesc21"name="label" font="Interface/Fonts/Impact.fnt"text="Very hilly area with trees" x="5"y="30"color="#960233"/>
                        <control id="newgamedesc22"name="label" font="Interface/Fonts/Impact.fnt"text="and nearly nothing else in sight" x="5"y="55"color="#960233"/>
                        <control id="newgamedesc2Availability"name="label" font="Interface/Fonts/Impact.fnt"text="SOON!" x="305"y="55"color="#FF0000"/>
                        <image filename="Interface/Nifty/cross.png"x="0"y="0" childLayout="absolute" width="100%" height="100%">
                            <interact onClick=""/>
                        </image>
                        <interact onClick=""/>
                    </panel>
                    <panel x="1%"y="270"id="newgame3"valign="top"align="left"height="120" width="98%" backgroundColor="#8FBF5C" childLayout="absolute"visibleToMouse="true">
                        <control id="newgamename3"name="label" font="Interface/Fonts/Impact.fnt"text="UNKNOWN" x="5"y="5" color="#FF4D88"/>
                        <control id="newgamedesc31"name="label" font="Interface/Fonts/Impact.fnt"text="Unexplored land" x="5"y="30"color="#960233"/>
                        <control id="newgamedesc32"name="label" font="Interface/Fonts/Impact.fnt"text="what will it be?" x="5"y="55"color="#960233"/>
                        <control id="newgamedesc3Availability"name="label" font="Interface/Fonts/Impact.fnt"text="SOON!" x="305"y="55"color="#FF0000"/>
                        <image filename="Interface/Nifty/cross.png"x="0"y="0" childLayout="absolute" width="100%" height="100%">
                            <interact onClick=""/>
                        </image>
                        <interact onClick=""/>
                    </panel>
                </panel>
            </control>
            <control id="loadgamewindow" name="window"title="LOAD SAVED GAMES"width="260"height="300"x="500"y="100"hideOnClose="true"closeable="true">
                <panel x="0"y="0"id="loadgamepanel"valign="top"align="left"backgroundColor="#222f" childLayout="absolute"visibleToMouse="true">
                    <control id="loadgameinfotext"name="label" font="Interface/Fonts/Impact.fnt"text="Double click to load a file!" x="38"y="2" color="#aaaf"/>
                    <control id="loadgamelistbox" name="listBox" vertical="on" width="100%"height="100%"horizontal="off" displayItems="9" selection="Single" x="0"y="74"/>
                </panel>
            </control>
        </layer>
    </screen>
    <screen id="hud"controller="intopark.GUI.IngameHUD">
        <layer id="background" height="100%" width="100%" childLayout="center">
            <image filename="Interface/Nifty/Transparent.png"  width="100%" height="100%"></image>
        </layer>
        <layer id="buttonlayer" x="0"y="0"height="64" width="100%" childLayout="absolute">
            <panel id="buttons"x="0"y="0"height="64" width="100%" backgroundColor="#999f" childLayout="absolute"visibleToMouse="true">
                <image filename="Interface/Terrain/Icon.png"x="0"y="0" childLayout="absolute" width="64" height="64">
                    <interact onClick="toggleShovelWindow()"/>
                </image>
                <image filename="Interface/Roads/uphill.png"x="65"y="0" childLayout="absolute" width="64" height="64">
                    <interact onClick="toggleRoadWindow()"/>
                </image>
                <image filename="Interface/Rides/Icon.png"x="130"y="0" childLayout="absolute" width="64" height="64">
                    <interact onClick="toggleShopWindow()"/>
                </image>
                <image filename="Interface/money/bulldozer.png"x="195"y="0" childLayout="absolute" width="64" height="64">
                    <interact onClick="clickDemolishbutton()"/>
                </image>
                <image filename="Interface/Decoration/Icon.png"x="260"y="0" childLayout="absolute" width="64" height="64">
                    <interact onClick="toggleDecorationWindow()"/>
                </image>
                <image filename="Interface/Nifty/Save.png"x="325"y="0" childLayout="absolute" width="64" height="64">
                    <interact onClick="testSave()"/>
                </image>
                <image id="clickmodeindicator"filename="Interface/money/bulldozer.png"x="500"y="0" childLayout="absolute" width="64" height="64">
                </image>
                <image filename="Interface/NPC/Icon.png"x="390"y="0" childLayout="absolute" width="64" height="64">
                    <interact onClick="toggleNPCListWindow()"/>
                </image>
                <image id="moneyicon" filename="Interface/money/Icon.png"x="600"y="0" childLayout="absolute" width="300" height="64">
                </image>
                <control id="guestnumtext"name="label" text="10000" x="650"y="4"/>
                <control id="moneytext"name="label" text="10000000.00" x="650"y="4"/>
                <control id="loantext"name="label" text="1000000.00" x="650"y="38"/>
            </panel>
        </layer>
        <layer id="windows" width="200"height="300"childLayout="absolute">
            <control id="shovelWindow" name="window"title="Shovel"width="200"height="130"x="200"y="200"hideOnClose="true"closeable="false">
                <panel id="shovelpanel"valign="top"align="left"height="100%" width="100%" backgroundColor="#555f" childLayout="absolute"visibleToMouse="true">
                    <control id="shoveltextures" x="4"y="4"name="imageSelect" width="92" imageWidth="48" imageHeight="48" imageList="Textures/grasstexture.png,Textures/rocktexture.png" />
                    <control id="shovelusetexture"name="label" text="Texture" x="100"y="4"/>
                    <control id="shoveltexturemode" name="checkbox" x="174"y="4"/>
                    <image id="plusshovelsize"filename="Interface/Terrain/plus.png"x="4"y="56" childLayout="absolute" width="32" height="32">
                        <interact onClick="toggleShovelSizePlus()"/>
                    </image>
                    <image id="minusshovelsize"filename="Interface/Terrain/minus.png"x="66"y="56" childLayout="absolute" width="32" height="32">
                        <interact onClick="toggleShovelSizeMinus()"/>
                    </image>
                    <control id="shovelbrushsizeprefix"name="label" text="Brush size: " x="100"y="56"/>
                    <control id="shovelbrushsize"name="label" text="1" x="180"y="56"/>
                </panel>
            </control>
            <control id="roadWindow" name="window"title="Roads"width="200"height="500"x="500"y="200"hideOnClose="true"closeable="false">
                <panel id="roadpanel"valign="top"align="left"height="100%" width="100%" backgroundColor="#999f" childLayout="absolute"visibleToMouse="true">
                    <image id="roadkehikkoimg"filename="Interface/Roads/kehikko.png"x="10"y="90" childLayout="absolute" width="159" height="159">
                    </image>
                    <image id="roadupimg"filename="Interface/Roads/up.png"x="14"y="94" childLayout="absolute" width="72" height="72">
                        <interact onClick="roadDirectionUp()">
                        </interact>
                        <effect>
                            <onCustom name="border" border="2px" color="#ffff" timeType="infinite"length="infinite"oneShot="true"/>
                        </effect>
                    </image>
                    <image id="roadrightimg"filename="Interface/Roads/right.png"x="93"y="94" childLayout="absolute" width="72" height="72"visibleToMouse="true">
                        <interact onClick="roadDirectionRight()">
                        </interact>
                        <effect>
                            <onCustom name="border" border="2px" color="#ffff" timeType="infinite"length="infinite"oneShot="true"/>
                        </effect>
                    </image>
                    <image id="roadleftimg"filename="Interface/Roads/left.png"x="14"y="173" childLayout="absolute" width="72" height="72"visibleToMouse="true">
                        <interact onClick="roadDirectionLeft()">
                        </interact>
                        <effect>
                            <onCustom name="border" border="2px" color="#ffff" timeType="infinite"length="infinite"oneShot="true"/>
                        </effect>
                    </image>
                    <image id="roaddownimg"filename="Interface/Roads/down.png"x="93"y="173" childLayout="absolute" width="72" height="72"visibleToMouse="true">
                        <interact onClick="roadDirectionDown()">
                        </interact>
                        <effect>
                            <onCustom name="border" border="2px" color="#ffff" timeType="infinite"length="infinite"oneShot="true"/>
                        </effect>
                    </image>
                    <image id="roadkehikkosmallimg"filename="Interface/Roads/kehikkosmall.png"x="8"y="256" childLayout="absolute" width="166" height="56"visibleToMouse="true">
                    </image>
                    <image id="roaddownhillimg"filename="Interface/Roads/downhill.png"x="12"y="260" childLayout="absolute" width="48" height="48"visibleToMouse="true">
                        <interact onClick="roadDownHill()">
                        </interact>
                        <effect>
                            <onCustom name="border" border="2px" color="#ffff" timeType="infinite"length="infinite"oneShot="true"/>
                        </effect>
                    </image>
                    <image id="roadflatimg"filename="Interface/Roads/flat.png"x="67"y="260" childLayout="absolute" width="48" height="48"visibleToMouse="true">
                        <interact onClick="roadFlatHill()">
                        </interact>
                        <effect>
                            <onCustom name="border" border="2px" color="#ffff" timeType="infinite"length="infinite"oneShot="true"/>
                        </effect>
                    </image>
                    <image id="roaduphillimg"filename="Interface/Roads/uphill.png"x="122"y="260" childLayout="absolute" width="48" height="48"visibleToMouse="true">
                        <interact onClick="roadUpHill()">
                        </interact>
                        <effect>
                            <onCustom name="border" border="2px" color="#ffff" timeType="infinite"length="infinite"oneShot="true"/>
                        </effect>
                    </image>
                    <image filename="Interface/Roads/build.png"x="6"y="320" childLayout="absolute" height="64"width="170"visibleToMouse="true">
                        <interact onClick="buildButton()">
                        </interact>
                    </image>
                    <image filename="Interface/Roads/kehikkoala.png"x="20"y="388" childLayout="absolute" width="143" height="72"visibleToMouse="true">
                    </image>
                    <image filename="Interface/Roads/selectspot.png"x="24"y="392" childLayout="absolute" width="64" height="64"visibleToMouse="true">
                        <interact onClick="selectionButton()">
                        </interact>
                    </image>
                    <image filename="Interface/Roads/mode.png"x="95"y="392" childLayout="absolute" width="64" height="64"visibleToMouse="true">
                        <interact onClick="roadModeButton()">
                        </interact>
                    </image>
                    <control id="queroad" name="checkbox" x="10"y="20"/>
                </panel>
            </control>
            <control id="shopWindow" name="window"title="Buildings"width="1000"height="600"x="200"y="200"hideOnClose="true"closeable="false">
                <panel id="shope_rootpanel"valign="top"align="left"height="100%" width="100%" x="0"y="0"backgroundColor="#1c1b18" childLayout="absolute"visibleToMouse="true">
                    <panel id="shope_tabspanel"valign="top"align="left"height="100%" width="590" x="0"y="0"backgroundColor="#1c1b18" childLayout="absolute"visibleToMouse="true"childClip="true">
                        <control id="shope_tabs" name="tabGroup" buttonWidth="1" buttonHeight="1"x="0"y="0">
                            <control id="shope_tab_1" name="tab" caption="Food places"x="0"y="0" height="100%" width="100%">
                                <panel id="shope_tab_1_panel"valign="top"align="left"height="600" width="590" x="0"y="0"backgroundColor="#1c1b18" childLayout="absolute"visibleToMouse="true">
                                    <panel id="shope_tab_1_desc"valign="top"align="left"height="140" width="90%" x="0"y="0"backgroundColor="#222f" childLayout="absolute"visibleToMouse="true">
                                        <control id="shope_tab_1_descline1"name="label" text="Food Shops are small and compact buildings which are used to serve food" x="5"y="5" color="#ffff"/>
                                        <control id="shope_tab_1_descline2"name="label" text="and drinks to your guests. There are plenty of shops to choose from" x="5"y="29" color="#ffff"/>
                                        <control id="shope_tab_1_descline3"name="label" text="so try to find something that is suitable for your park!" x="5"y="53" color="#ffff"/>
                                        <effect>
                                            <onActive name="border" border="2px" color="#000f" timeType="infinite"/>
                                        </effect>
                                    </panel>
                                    <panel id="shope_tab_1_row_1"valign="top"align="left"height="66" width="90%" x="0"y="150"backgroundColor="#222f" childLayout="absolute"visibleToMouse="true">
                                        <image id="shope_tab_1_item_1"filename="Interface/buildings/Icon.png"x="1"y="1" childLayout="absolute" width="64" height="64"visibleToMouse="true">
                                            <interact onClick="selectbuilding(MEATBALLS)"/>
                                            <effect>
                                                <onHover name="border" border="1px" color="#822f"/>
                                            </effect>
                                        </image>
                                        <image id="shope_tab_1_item_2"filename="Interface/buildings/Icon.png"x="66"y="1" childLayout="absolute" width="64" height="64"visibleToMouse="true">
                                            <interact onClick="selectbuilding(CAFE)"/>
                                            <effect>
                                                <onHover name="border" border="1px" color="#822f"/>
                                            </effect>
                                        </image>
                                        <image id="shope_tab_1_item_3"filename="Interface/buildings/Icon.png"x="133"y="1" childLayout="absolute" width="64" height="64"visibleToMouse="true">
                                            <interact onClick="selectbuilding(NAKK_KIOSK)"/>
                                            <effect>
                                                <onHover name="border" border="1px" color="#822f"/>
                                            </effect>
                                        </image>
                                        <image id="shope_tab_1_item_4"filename="Interface/buildings/Icon.png"x="199"y="1" childLayout="absolute" width="64" height="64"visibleToMouse="true">
                                            <interact onClick="selectbuilding(CANDY_STREET)"/>
                                            <effect>
                                                <onHover name="border" border="1px" color="#822f"/>
                                            </effect>
                                        </image>
                                        <image id="shope_tab_1_item_5"filename="Interface/buildings/Icon.png"x="265"y="1" childLayout="absolute" width="64" height="64"visibleToMouse="true">
                                            <interact onClick="selectbuilding(POPCORNVAN)"/>
                                            <effect>
                                                <onHover name="border" border="1px" color="#822f"/>
                                            </effect>
                                        </image>
                                        <image id="shope_tab_1_item_6"filename="Interface/buildings/Icon.png"x="331"y="1" childLayout="absolute" width="64" height="64"visibleToMouse="true">
                                            <interact onClick="selectbuilding(TRACHFOOD)"/>
                                            <effect>
                                                <onHover name="border" border="1px" color="#822f"/>
                                            </effect>
                                        </image>
                                        <image id="shope_tab_1_item_7"filename="Interface/buildings/Icon.png"x="397"y="1" childLayout="absolute" width="64" height="64"visibleToMouse="true">
                                            <interact onClick="selectbuilding(SODAMACHINE)"/>
                                            <effect>
                                                <onHover name="border" border="1px" color="#822f"/>
                                            </effect>
                                        </image>
                                        <image id="shope_tab_1_item_8"filename="Interface/buildings/Icon.png"x="463"y="1" childLayout="absolute" width="64" height="64"visibleToMouse="true">
                                            <interact onClick="selectbuilding(MILKSHJAKE)"/>
                                            <effect>
                                                <onHover name="border" border="1px" color="#822f"/>
                                            </effect>
                                        </image>
                                        <effect>
                                            <onActive name="border" border="1px" color="#000f" timeType="infinite"/>
                                        </effect>
                                    </panel>
                                    <panel id="shope_tab_1_row_2"valign="top"align="left"height="66" width="90%" x="0"y="218"backgroundColor="#222f" childLayout="absolute"visibleToMouse="true">
                                        <image id="shope_tab_1_item_9"filename="Interface/buildings/Icon.png"x="1"y="1" childLayout="absolute" width="64" height="64"visibleToMouse="true">
                                            <interact onClick="selectbuilding(CHICKEM)"/>
                                            <effect>
                                                <onHover name="border" border="1px" color="#822f"/>
                                            </effect>
                                        </image>
                                        <image id="shope_tab_1_item_10"filename="Interface/buildings/Icon.png"x="66"y="1" childLayout="absolute" width="64" height="64"visibleToMouse="true">
                                            <interact onClick="selectbuilding(SWEETFRUITS)"/>
                                            <effect>
                                                <onHover name="border" border="1px" color="#822f"/>
                                            </effect>
                                        </image>
                                        <image id="shope_tab_1_item_11"filename="Interface/buildings/Icon.png"x="133"y="1" childLayout="absolute" width="64" height="64"visibleToMouse="true">
                                            <interact onClick="selectbuilding(WRAP_PLACE)"/>
                                            <effect>
                                                <onHover name="border" border="1px" color="#822f"/>
                                            </effect>
                                        </image>
                                        <image id="shope_tab_1_item_12"filename="Interface/buildings/Icon.png"x="199"y="1" childLayout="absolute" width="64" height="64"visibleToMouse="true">
                                            <interact onClick="selectbuilding(INTOS_ICECREAM)"/>
                                            <effect>
                                                <onHover name="border" border="1px" color="#822f"/>
                                            </effect>
                                        </image>
                                        <image id="shope_tab_1_item_13"filename="Interface/buildings/Icon.png"x="265"y="1" childLayout="absolute" width="64" height="64"visibleToMouse="true">
                                            <interact onClick="selectbuilding(PASTRY_SHOP)"/>
                                            <effect>
                                                <onHover name="border" border="1px" color="#822f"/>
                                            </effect>
                                        </image>
                                        <image id="shope_tab_1_item_14"filename="Interface/buildings/Icon.png"x="331"y="1" childLayout="absolute" width="64" height="64"visibleToMouse="true">
                                            <interact onClick="selectbuilding(NORMAI_FOOD)"/>
                                            <effect>
                                                <onHover name="border" border="1px" color="#822f"/>
                                            </effect>
                                        </image>
                                        <image id="shope_tab_1_item_15"filename="Interface/buildings/Icon.png"x="397"y="1" childLayout="absolute" width="64" height="64"visibleToMouse="true">
                                            <interact onClick="selectbuilding(SWEETCORN)"/>
                                            <effect>
                                                <onHover name="border" border="1px" color="#822f"/>
                                            </effect>
                                        </image>
                                        <image id="shope_tab_1_item_16"filename="Interface/buildings/Icon.png"x="463"y="1" childLayout="absolute" width="64" height="64"visibleToMouse="true">
                                            <interact onClick="selectbuilding(CHIPS_N_CHICKEN)"/>
                                            <effect>
                                                <onHover name="border" border="1px" color="#822f"/>
                                            </effect>
                                        </image>
                                        <effect>
                                            <onActive name="border" border="1px" color="#000f" timeType="infinite"/>
                                        </effect>
                                    </panel>
                                </panel>
                            </control>
                            <control id="shope_tab_2" name="tab" caption="Other shops"x="0"y="0" height="100%" width="100%">
                                <panel id="shope_tab_2_panel"valign="top"align="left"height="600" width="590" x="0"y="0"backgroundColor="#1c1b18" childLayout="absolute"visibleToMouse="true">
                                    <panel id="shope_tab_2_desc"valign="top"align="left"height="140" width="90%" x="0"y="0"backgroundColor="#222f" childLayout="absolute"visibleToMouse="true">
                                        <control id="shope_tab_2_descline1"name="label" text="Everything from essential buildings such as toilet info kiosk and news stand to the" x="5"y="5" color="#ffff"/>
                                        <control id="shope_tab_2_descline2"name="label" text="extra services like balloon stands and can throwing competitions for your" x="5"y="29" color="#ffff"/>
                                        <control id="shope_tab_2_descline3"name="label" text="visitors to enjoy! " x="5"y="53" color="#ffff"/>
                                        <effect>
                                            <onActive name="border" border="2px" color="#000f" timeType="infinite"/>
                                        </effect>
                                    </panel>
                                    <panel id="shope_tab_2_row_1"valign="top"align="left"height="66" width="90%" x="0"y="150"backgroundColor="#222f" childLayout="absolute"visibleToMouse="true">
                                        <image id="shope_tab_2_item_1"filename="Interface/buildings/Icon.png"x="1"y="1" childLayout="absolute" width="64" height="64"visibleToMouse="true">
                                            <interact onClick="selectbuilding(NULL)"/>
                                            <effect>
                                                <onHover name="border" border="1px" color="#822f"/>
                                            </effect>
                                        </image>
                                        <image id="shope_tab_2_item_2"filename="Interface/buildings/Icon.png"x="66"y="1" childLayout="absolute" width="64" height="64"visibleToMouse="true">
                                            <interact onClick="selectbuilding(NULL)"/>
                                            <effect>
                                                <onHover name="border" border="1px" color="#822f"/>
                                            </effect>
                                        </image>
                                        <image id="shope_tab_2_item_3"filename="Interface/buildings/Icon.png"x="133"y="1" childLayout="absolute" width="64" height="64"visibleToMouse="true">
                                            <interact onClick="selectbuilding(NULL)"/>
                                            <effect>
                                                <onHover name="border" border="1px" color="#822f"/>
                                            </effect>
                                        </image>
                                        <image id="shope_tab_2_item_4"filename="Interface/buildings/Icon.png"x="199"y="1" childLayout="absolute" width="64" height="64"visibleToMouse="true">
                                            <interact onClick="selectbuilding(NULL)"/>
                                            <effect>
                                                <onHover name="border" border="1px" color="#822f"/>
                                            </effect>
                                        </image>
                                        <image id="shope_tab_2_item_5"filename="Interface/buildings/Icon.png"x="265"y="1" childLayout="absolute" width="64" height="64"visibleToMouse="true">
                                            <interact onClick="selectbuilding()"/>
                                            <effect>
                                                <onHover name="border" border="1px" color="#822f"/>
                                            </effect>
                                        </image>
                                        <image id="shope_tab_2_item_6"filename="Interface/buildings/Icon.png"x="331"y="1" childLayout="absolute" width="64" height="64"visibleToMouse="true">
                                            <interact onClick="selectbuilding(NULL)"/>
                                            <effect>
                                                <onHover name="border" border="1px" color="#822f"/>
                                            </effect>
                                        </image>
                                        <image id="shope_tab_2_item_7"filename="Interface/buildings/Icon.png"x="397"y="1" childLayout="absolute" width="64" height="64"visibleToMouse="true">
                                            <interact onClick="selectbuilding(NULL)"/>
                                            <effect>
                                                <onHover name="border" border="1px" color="#822f"/>
                                            </effect>
                                        </image>
                                        <image id="shope_tab_2_item_8"filename="Interface/buildings/Icon.png"x="463"y="1" childLayout="absolute" width="64" height="64"visibleToMouse="true">
                                            <interact onClick="selectbuilding(NULL)"/>
                                            <effect>
                                                <onHover name="border" border="1px" color="#822f"/>
                                            </effect>
                                        </image>
                                        <effect>
                                            <onActive name="border" border="1px" color="#000f" timeType="infinite"/>
                                        </effect>
                                    </panel>
                                    <panel id="shope_tab_2_row_2"valign="top"align="left"height="66" width="90%" x="0"y="218"backgroundColor="#222f" childLayout="absolute"visibleToMouse="true">
                                        <effect>
                                            <onActive name="border" border="1px" color="#000f" timeType="infinite"/>
                                        </effect>
                                    </panel>
                                </panel>
                            </control>
                            <control id="shope_tab_3" name="tab" caption="Rides"x="0"y="0" height="100%" width="100%">
                                <panel id="shope_tab_3_panel"valign="top"align="left"height="600" width="590" x="0"y="0"backgroundColor="#1c1b18" childLayout="absolute"visibleToMouse="true">
                                    <panel id="shope_tab_3_desc"valign="top"align="left"height="140" width="90%" x="0"y="0"backgroundColor="#222f" childLayout="absolute"visibleToMouse="true">
                                        <control id="shope_tab_3_descline1"name="label" text="These mechanical machines provide entertainment for nearly everyone. These" x="5"y="5" color="#ffff"/>
                                        <control id="shope_tab_3_descline2"name="label" text="are the absolute reasons to come to a theme park. Have you seen " x="5"y="29" color="#ffff"/>
                                        <control id="shope_tab_3_descline3"name="label" text="the Pirate ship or the Haunted house? Remember that good rides come with" x="5"y="53" color="#ffff"/>
                                        <control id="shope_tab_3_descline4"name="label" text="a good cost." x="5"y="77" color="#ffff"/>
                                        <effect>
                                            <onActive name="border" border="2px" color="#000f" timeType="infinite"/>
                                        </effect>
                                    </panel>
                                    <panel id="shope_tab_3_row_1"valign="top"align="left"height="66" width="90%" x="0"y="150"backgroundColor="#222f" childLayout="absolute"visibleToMouse="true">
                                        <image id="shope_tab_3_item_1"filename="Interface/buildings/Icon.png"x="1"y="1" childLayout="absolute" width="64" height="64"visibleToMouse="true">
                                            <interact onClick="selectbuilding(CHESSCENTER)"/>
                                            <effect>
                                                <onHover name="border" border="1px" color="#822f"/>
                                            </effect>
                                        </image>
                                        <image id="shope_tab_3_item_2"filename="Interface/buildings/Icon.png"x="66"y="1" childLayout="absolute" width="64" height="64"visibleToMouse="true">
                                            <interact onClick="selectbuilding(PIRATESHIP)"/>
                                            <effect>
                                                <onHover name="border" border="1px" color="#822f"/>
                                            </effect>
                                        </image>
                                        <image id="shope_tab_3_item_3"filename="Interface/buildings/Icon.png"x="133"y="1" childLayout="absolute" width="64" height="64"visibleToMouse="true">
                                            <interact onClick="selectbuilding(HAUNTEDHOUSE)"/>
                                            <effect>
                                                <onHover name="border" border="1px" color="#822f"/>
                                            </effect>
                                        </image>
                                        <image id="shope_tab_3_item_4"filename="Interface/buildings/Icon.png"x="199"y="1" childLayout="absolute" width="64" height="64"visibleToMouse="true">
                                            <interact onClick="selectbuilding()"/>
                                            <effect>
                                                <onHover name="border" border="1px" color="#822f"/>
                                            </effect>
                                        </image>
                                        <image id="shope_tab_3_item_5"filename="Interface/buildings/Icon.png"x="265"y="1" childLayout="absolute" width="64" height="64"visibleToMouse="true">
                                            <interact onClick="selectbuilding()"/>
                                            <effect>
                                                <onHover name="border" border="1px" color="#822f"/>
                                            </effect>
                                        </image>
                                        <image id="shope_tab_3_item_6"filename="Interface/buildings/Icon.png"x="331"y="1" childLayout="absolute" width="64" height="64"visibleToMouse="true">
                                            <interact onClick="selectbuilding()"/>
                                            <effect>
                                                <onHover name="border" border="1px" color="#822f"/>
                                            </effect>
                                        </image>
                                        <image id="shope_tab_3_item_7"filename="Interface/buildings/Icon.png"x="397"y="1" childLayout="absolute" width="64" height="64"visibleToMouse="true">
                                            <interact onClick="selectbuilding()"/>
                                            <effect>
                                                <onHover name="border" border="1px" color="#822f"/>
                                            </effect>
                                        </image>
                                        <image id="shope_tab_3_item_8"filename="Interface/buildings/Icon.png"x="463"y="1" childLayout="absolute" width="64" height="64"visibleToMouse="true">
                                            <interact onClick="selectbuilding()"/>
                                            <effect>
                                                <onHover name="border" border="1px" color="#822f"/>
                                            </effect>
                                        </image>
                                        <effect>
                                            <onActive name="border" border="1px" color="#000f" timeType="infinite"/>
                                        </effect>
                                    </panel>
                                    <panel id="shope_tab_3_row_2"valign="top"align="left"height="66" width="90%" x="0"y="218"backgroundColor="#222f" childLayout="absolute"visibleToMouse="true">
                                        <effect>
                                            <onActive name="border" border="1px" color="#000f" timeType="infinite"/>
                                        </effect>
                                    </panel>
                                </panel>
                            </control>
                            <!--
                            <control id="shope_tab_4" name="tab" caption="rides 2"x="0"y="0" height="100%" width="100%">
                                <panel id="shope_tab_4_panel"valign="top"align="left"height="600" width="590" x="0"y="0"backgroundColor="#1c1b18" childLayout="absolute"visibleToMouse="true">
                                    <panel id="shope_tab_4_desc"valign="top"align="left"height="140" width="90%" x="0"y="0"backgroundColor="#222f" childLayout="absolute"visibleToMouse="true">
                                        <control id="shope_tab_4_descline1"name="label" text="" x="5"y="5" color="#ffff"/>
                                        <control id="shope_tab_4_descline2"name="label" text="" x="5"y="29" color="#ffff"/>
                                        <control id="shope_tab_4_descline3"name="label" text="" x="5"y="53" color="#ffff"/>
                                        <effect>
                                            <onActive name="border" border="2px" color="#000f" timeType="infinite"/>
                                        </effect>
                                    </panel>
                                    <panel id="shope_tab_4_row_1"valign="top"align="left"height="66" width="90%" x="0"y="150"backgroundColor="#222f" childLayout="absolute"visibleToMouse="true">
                                        <effect>
                                            <onActive name="border" border="1px" color="#000f" timeType="infinite"/>
                                        </effect>
                                    </panel>
                                    <panel id="shope_tab_4_row_2"valign="top"align="left"height="66" width="90%" x="0"y="218"backgroundColor="#222f" childLayout="absolute"visibleToMouse="true">
                                        <effect>
                                            <onActive name="border" border="1px" color="#000f" timeType="infinite"/>
                                        </effect>
                                    </panel>
                                </panel>
                            </control>
                            <control id="shope_tab_5" name="tab" caption="Other"x="0"y="0" height="100%" width="100%">
                                <panel id="shope_tab_5_panel"valign="top"align="left"height="600" width="590" x="0"y="0"backgroundColor="#1c1b18" childLayout="absolute"visibleToMouse="true">
                                    <panel id="shope_tab_5_desc"valign="top"align="left"height="140" width="90%" x="0"y="0"backgroundColor="#222f" childLayout="absolute"visibleToMouse="true">
                                        <control id="shope_tab_5_descline1"name="label" text="" x="5"y="5" color="#ffff"/>
                                        <control id="shope_tab_5_descline2"name="label" text="" x="5"y="29" color="#ffff"/>
                                        <control id="shope_tab_5_descline3"name="label" text="" x="5"y="53" color="#ffff"/>
                                        <effect>
                                            <onActive name="border" border="2px" color="#000f" timeType="infinite"/>
                                        </effect>
                                    </panel>
                                    <panel id="shope_tab_5_row_1"valign="top"align="left"height="66" width="90%" x="0"y="150"backgroundColor="#222f" childLayout="absolute"visibleToMouse="true">
                                        <effect>
                                            <onActive name="border" border="1px" color="#000f" timeType="infinite"/>
                                        </effect>
                                    </panel>
                                    <panel id="shope_tab_5_row_2"valign="top"align="left"height="66" width="90%" x="0"y="218"backgroundColor="#222f" childLayout="absolute"visibleToMouse="true">
                                        <effect>
                                            <onActive name="border" border="1px" color="#000f" timeType="infinite"/>
                                        </effect>
                                    </panel>
                                </panel>
                            </control>
                            -->
                        </control>
                    </panel>
                    <panel id="shopdescpanel"valign="top"align="left"height="500" width="380" x="600"y="60"backgroundColor="#1c1b18" childLayout="absolute"visibleToMouse="true">
                        <panel id="buildingDescImagePanel"valign="top"align="left"height="302" width="378" x="2"y="2"backgroundColor="#1c1b18" childLayout="absolute"visibleToMouse="true">
                            <image id="shopbigpic"filename="Interface/Shops/Noshoppic.png"x="1"y="1" childLayout="absolute" height="300"width="376"visibleToMouse="true"/>
                            <effect>
                                <onActive name="border" border="1px" color="#000f" timeType="infinite"/>
                            </effect>
                        </panel>
                        <panel id="buildingDescNamePanel"valign="top"align="left"height="30" width="378" x="2"y="320"backgroundColor="#1c1b18" childLayout="absolute"visibleToMouse="true" wrap="true">
                            <control id="buildingDescName"name="label" text="OOOOOOOOOOOOOOOOOOOOOOOOOOOOOOOOOOOOOOOOOOOOOOOOOOOOOOOOO" x="7"y="1" color="ffffff"/>
                            <effect>
                                <onActive name="border" border="1px" color="#000f" timeType="infinite"/>
                            </effect>
                        </panel>
                        <panel id="buildingDescPricePanel"valign="top"align="left"height="30" width="378" x="2"y="360"backgroundColor="#1c1b18" childLayout="absolute"visibleToMouse="true">
                            <control id="buildingDescPrice"name="label" text="OOOOOOOOOOOOOOOOOOOOOOOOOOOOOOOOOOOOOOOOOOOOOOOOOOOOOOOOO" x="7"y="1" color="ffffff"/>
                            <effect>
                                <onActive name="border" border="1px" color="#000f" timeType="infinite"/>
                            </effect>
                        </panel>
                        <panel id="buildingDescDescPanel"valign="top"align="left"height="100" width="378" x="2"y="400"backgroundColor="#1c1b18" childLayout="absolute"visibleToMouse="true">
                            <control id="buildingDescDesc1"name="label" text="OOOOOOOOOOOOOOOOOOOOOOOOOOOOOOOOOOOOOOOOOOOOOOOOOOOOOOOOO" x="7"y="1" color="ffffff"/>
                            <control id="buildingDescDesc2"name="label" text="OOOOOOOOOOOOOOOOOOOOOOOOOOOOOOOOOOOOOOOOOOOOOOOOOOOOOOOOO" x="7"y="25" color="ffffff"/>
                            <control id="buildingDescDesc3"name="label" text="OOOOOOOOOOOOOOOOOOOOOOOOOOOOOOOOOOOOOOOOOOOOOOOOOOOOOOOOO" x="7"y="49" color="ffffff"/>
                            <control id="buildingDescDesc4"name="label" text="OOOOOOOOOOOOOOOOOOOOOOOOOOOOOOOOOOOOOOOOOOOOOOOOOOOOOOOOO" x="7"y="73" color="ffffff"/>
                            <effect>
                                <onActive name="border" border="1px" color="#000f" timeType="infinite"/>
                            </effect>
                        </panel>

                    </panel>
                </panel>
            </control>
            <control id="guesttemplate" name="window"title="Guest"width="496"height="400"x="200"y="200"closeable="true"hideOnClose="true">
                <panel id="g_rootpanel"valign="top"align="left"height="100%" width="100%" x="0"y="0"backgroundColor="#5C5C5C" childLayout="absolute"visibleToMouse="true">
                    <panel id="g_tabspanel"valign="top"align="left"height="100%" width="100%" x="0"y="0"backgroundColor="#4A4949" childLayout="absolute"visibleToMouse="true"childClip="true">
                        <control id="guest_tabs" name="tabGroup" buttonWidth="1" buttonHeight="1"x="0"y="0">
                            <control id="g_tab_1" name="tab" caption="Information"x="0"y="0">
                                <panel id="g_tab_1_panel"valign="top"align="left"height="100%" width="100%" x="0"y="0"backgroundColor="#0000" childLayout="absolute"visibleToMouse="true">
                                    <image filename="Interface/NPC/face.png"x="0"y="10" childLayout="absolute" height="200"width="130"visibleToMouse="true">
                                        <effect>
                                            <onActive name="border" border="1px" color="#000f" timeType="infinite"/>
                                        </effect>
                                    </image>
                                        <control id="guestnameprefix"name="label" text="Name: " x="136"y="10" color="ffffff"/>
                                        <control id="guestname"name="label" text="Template name " x="180"y="10" color="ffffff"/>
                                        <control id="guestgenderprefix"name="label" text="Gender: " x="136"y="30" color="ffffff"/>
                                        <control id="guestgender"name="label" text="male/female " x="190"y="30" color="ffffff"/>
                                        <control id="guestageprefix"name="label"text="Age: " x="136"y="50" color="ffffff"/>
                                        <control id="guestage"name="label" text="adult/child" x="168"y="50" color="ffffff"/>
                                        <control id="guestwalletprefix"name="label" text="Money: " x="136"y="70" color="ffffff"/>
                                        <control id="guestwallet"name="label"text="90e" x="184"y="70" color="ffffff"/>
                                        <control id="gueststatusprefix"name="label" text="Feeling: " x="136"y="90" color="ffffff"/>
                                        <control id="gueststatus"name="label" text="awesome" x="186"y="90" color="ffffff"/>
                                        <control id="guestprefprefix"name="label"text="Ride preferences: " x="136"y="110" color="ffffff"/>
                                        <control id="guestpref"name="label" text="slow rides" x="250"y="110" color="ffffff"/>
                                        <control id="guestlastactionsprefix"name="label" text="Latest 5 actions: " x="136"y="130" color="ffffff"/>
                                        <control id="guestlastaction1"name="label" text="..." x="136"y="150" color="ffffff"/>
                                        <control id="guestlastaction2"name="label" text="..." x="136"y="170" color="ffffff"/>
                                        <control id="guestlastaction3"name="label" text="..." x="136"y="190" color="ffffff"/>
                                        <control id="guestlastaction4"name="label" text="..." x="136"y="210" color="ffffff"/>
                                        <control id="guestlastaction5"name="label" text="..." x="136"y="230" color="ffffff"/>
                                </panel>
                            </control>
                            <control id="g_tab_2" name="tab" caption="Feelings"x="0"y="0">
                                <panel id="g_tab_2_panel"valign="top"align="left"height="100%" width="100%" x="0"y="0"backgroundColor="#0000" childLayout="absolute"visibleToMouse="true">
                                    <control id="guesthungerprefix"name="label" text="Hunger: " x="44"y="16" color="ffffff"/>
                                    <image filename="Interface/NPC/foodIcon.png"x="10"y="10" childLayout="absolute" height="32"width="32"visibleToMouse="true"><effect><onActive name="border" border="1px" color="#000f" timeType="infinite"/></effect> </image>
                                    <control id="guesthunger"name="label" text="50" x="96"y="16" color="ffffff"/>
                                    <control id="guestthirstprefix"name="label" text="Thirst: " x="44"y="52" color="ffffff"/>
                                    <image filename="Interface/NPC/drinkIcon.png"x="10"y="46" childLayout="absolute" height="32"width="32"visibleToMouse="true"><effect><onActive name="border" border="1px" color="#000f" timeType="infinite"/></effect> </image>
                                    <control id="guestthirst"name="label" text="50" x="86"y="52" color="ffffff"/>
                                    <control id="guesthappynessprefix"name="label" text="Happyness: " x="44"y="88" color="ffffff"/>
                                    <image filename="Interface/NPC/happinessIcon.png"x="10"y="82" childLayout="absolute" height="32"width="32"visibleToMouse="true"><effect><onActive name="border" border="1px" color="#000f" timeType="infinite"/></effect> </image>
                                    <control id="guesthappyness"name="label" text="50" x="120"y="88" color="ffffff"/>
                                    <image filename="Interface/NPC/toiletIcon.png"x="10"y="118" childLayout="absolute" height="32"width="32"visibleToMouse="true"><effect><onActive name="border" border="1px" color="#000f" timeType="infinite"/></effect> </image>
                                    <control id="guesttoiletprefixt"name="label" text="Toilet: " x="44"y="124" color="ffffff"/>
                                    <control id="guesttoilet"name="label" text="20" x="88"y="124" color="ffffff"/>
                                    <control id="guestthink"name="label" text="Thoughts" font="Interface/Fonts/Impact.fnt" x="10"y="156" color="#FFF700"/>
                                    <control id="guestthinklistbox" name="listBox" vertical="on" width="450"height="100"horizontal="off" displayItems="7" selection="Single" x="10"y="180"/>
                                </panel>
                            </control>
                            <control id="g_tab_3" name="tab" caption="Actions"x="0"y="0">
                                <panel id="g_tab_3_panel"valign="top"align="left"height="100%" width="100%" x="0"y="0"backgroundColor="#0000" childLayout="absolute"visibleToMouse="true">
                                    <control id="guestnametextfieldprefix"name="label" text="Change name:" x="10"y="10" color="ffffff"/>
                                    <control id="guestnametextfield"name="textfield" maxLength="50" x="120"y="10"height="24" width="200" />
                                </panel>
                            </control>
                            <control id="g_tab_4" name="tab" caption="Inventory"x="0"y="0">
                                <panel id="g_tab_4_panel"valign="top"align="left"height="100%" width="100%" x="0"y="0"backgroundColor="#0000" childLayout="absolute"visibleToMouse="true">
                                    <control id="guestinventoryprefix"name="label" text="Inventory: " x="0"y="10" color="ffffff"/>
                                    <control id="guestinventory1"name="label" text="" x="20"y="40" color="ffffff"/>
                                    <control id="guestinventory2"name="label" text="" x="20"y="70" color="ffffff"/>
                                    <control id="guestinventory3"name="label" text="" x="20"y="100" color="ffffff"/>
                                    <control id="guestinventory4"name="label" text="" x="20"y="130" color="ffffff"/>
                                    <control id="guestinventory5"name="label" text="" x="20"y="160" color="ffffff"/>
                                    <control id="guestinventory6"name="label" text="" x="20"y="190" color="ffffff"/>
                                    <control id="guestinventory7"name="label" text="" x="20"y="220" color="ffffff"/>
                                    <control id="guestinventory8"name="label" text="" x="20"y="250" color="ffffff"/>
                                    <control id="guestinventory9"name="label" text="" x="20"y="280" color="ffffff"/>
                                </panel>
                            </control>
                            <!---
                            <control id="g_tab_5" name="tab" caption="More.."x="0"y="0">
                                <panel id="g_tab_5_panel"valign="top"align="left"height="100%" width="100%" x="0"y="0"backgroundColor="#1c1b18" childLayout="absolute"visibleToMouse="true">

                                </panel>
                            </control>
                            -->
                        </control>
                    </panel>
                </panel>
            </control>
            <control id="shoptemplate" name="window"title="Shop"width="496"height="400"x="200"y="200"closeable="true"hideOnClose="true">
                <panel id="s_rootpanel"valign="top"align="left"height="100%" width="100%" x="0"y="0"backgroundColor="#4A4949" childLayout="absolute"visibleToMouse="true">
                    <panel id="s_tabspanel"valign="top"align="left"height="100%" width="100%" x="0"y="0"backgroundColor="#4A4949" childLayout="absolute"visibleToMouse="true"childClip="true">
                        <control id="s_tabs" name="tabGroup" buttonWidth="1" buttonHeight="1"x="0"y="0">
                            <control id="s_tab_1" name="tab" caption="Information"x="0"y="0">
                                <panel id="s_tab_1_panel"valign="top"align="left"height="100%" width="100%" x="0"y="0"backgroundColor="#0000" childLayout="absolute"visibleToMouse="true">
                                        <control id="shopnameprefix"name="label" text="Name: " x="0"y="10" color="ffffff"/>
                                        <control id="shopname"name="label" text="Template name " x="42"y="10" color="ffffff"/>
                                        <control id="shoptypeprefix"name="label" text="Type: " x="0"y="30" color="ffffff"/>
                                        <control id="shoptype"name="label" text="Template type " x="36"y="30" color="ffffff"/>
                                        <control id="shoplocationprefix"name="label" text="Location: " x="0"y="50" color="ffffff"/>
                                        <control id="shoplocation"name="label" text="Unknown location" x="62"y="50" color="ffffff"/>
                                        <control id="shopmoneyearnprefix"name="label" text="Profit: " x="0"y="70" color="ffffff"/>
                                        <control id="shopmoneyearn"name="label" text="-100 " x="40"y="70" color="ffffff"/>
                                        <control id="shopbuiltprefix"name="label" text="Built: " x="0"y="90" color="ffffff"/>
                                        <control id="shopbuilt"name="label" text="1.1.2016" x="36"y="90" color="ffffff"/>
                                        <control id="shopproduct"name="label" font="Interface/Fonts/Impact.fnt"text="Products" x="0"y="170" color="#FFF700"/>
                                        <control id="shopproductlistbox" name="listBox" vertical="off" width="450"height="100"horizontal="off" displayItems="7" selection="Single" x="0"y="190"/>
                                </panel>
                            </control>
                            <control id="s_tab_2" name="tab" caption="Inspections"x="0"y="0">
                                <panel id="s_tab_2_panel"valign="top"align="left"height="100%" width="100%" x="0"y="0"backgroundColor="#0000" childLayout="absolute"visibleToMouse="true">
                                    <control id="shoplastinspectprefix"name="label" text="Last inspect: " x="0"y="10" color="#ffff"/>
                                    <control id="shoplastinspect"name="label" text="Not inspected " x="82"y="10" color="#ffff"/>
                                    <control id="shopworkingconditionsprefix"name="label" text="Working conditions: " x="0"y="30" color="#ffff"/>
                                    <control id="shopworkingconditions"name="label" text="Not inspected " x="130"y="30" color="#ffff"/>
                                    <control id="shopproductqualityprefix"name="label" text="Product quality: " x="0"y="50" color="#ffff"/>
                                    <control id="shopproductquality"name="label" text="Not inspected " x="102"y="50" color="#ffff"/>
                                    <control id="shopinspecttasteprefix"name="label" text="Left image: " x="0"y="70" color="#ffff"/>
                                    <control id="shopinspecttaste"name="label" text="Not inspected " x="80"y="70" color="#ffff"/>
                                    <control id="shopinspectedbyprefix"name="label" text="Inspected by: " x="0"y="90" color="#ffff"/>
                                    <control id="shopinspectedby"name="label" text="Not inspected" x="90"y="90" color="#ffff"/>
                                    <control id="shopupgrades"name="label" font="Interface/Fonts/Impact.fnt"text="Available Upgrades" x="300"y="8" color="#FFF700"/>
                                    <control id="shopupgradecheckbox1" name="checkbox" x="300"y="30"/>
                                    <control id="shopupgradecheckbox2" name="checkbox" x="300"y="50"/>
                                    <control id="shopupgradecheckbox3" name="checkbox" x="300"y="70"/>
                                    <control id="shopupgradecheckbox4" name="checkbox" x="300"y="90"/>
                                    <control id="shopupgradetext1"name="label" text="..." x="326"y="30" color="#ffff"/>
                                    <control id="shopupgradetext2"name="label" text="..." x="326"y="50" color="#ffff"/>
                                    <control id="shopupgradetext3"name="label" text="..." x="326"y="70" color="#ffff"/>
                                    <control id="shopupgradetext4"name="label" text="..." x="326"y="90" color="#ffff"/>
                                    <control id="shopnotices"name="label" font="Interface/Fonts/Impact.fnt"text="Special notices" x="0"y="170" color="#FFF700"/>
                                    <control id="shopnoticeslistbox" name="listBox" vertical="off" width="450"height="100"horizontal="off" displayItems="7" selection="Single" x="0"y="190"/>
                                </panel>
                            </control>
                            <control id="s_tab_3" name="tab" caption="Upgrades"x="0"y="0">
                                <panel id="s_tab_3_panel"valign="top"align="left"height="100%" width="100%" x="0"y="0"backgroundColor="#0000" childLayout="absolute"visibleToMouse="true">
                                    <control id="shopchangenametext"name="label" text="Change name" x="0"y="10" color="#ffff"/>
                                    <control id="shopnametextfield"name="textfield" maxLength="50" x="100"y="10"height="24" width="200" />
                                    <control id="shopchangeproducts"name="label" font="Interface/Fonts/Impact.fnt"text="Change Products" x="0"y="50" color="#FFF700"/>
                                    <control id="shopclicktochange"name="label" text="Click product to modify it." x="0"y="70" color="#ffff"/>
                                    <control id="shopmodifyproductslistbox" name="listBox" vertical="off" width="450"height="100"horizontal="off" displayItems="7" selection="Single" x="0"y="90"/>
                                    <control id="shopdemolishtext"name="label" text="Demolish" x="0"y="230" color="#ffff"/>
                                    <image filename="Interface/Rides/destroy.png"x="70"y="230" childLayout="absolute" height="32"width="32"visibleToMouse="true"><effect><onActive name="border" border="1px" color="#000f" timeType="infinite"/></effect> </image>
                                </panel>
                            </control>
                            <!--
                            <control id="s_tab_4" name="tab" caption="More.."x="0"y="0">
                                <panel id="s_tab_4_panel"valign="top"align="left"height="100%" width="100%" x="0"y="0"backgroundColor="#1c1b18" childLayout="absolute"visibleToMouse="true">

                                </panel>
                            </control>
                            -->
                        </control>
                    </panel>
                </panel>
            </control>
            <control id="ridetemplate" name="window"title="Ride"width="496"height="400"x="200"y="200"closeable="true"hideOnClose="true">
                <panel id="r_rootpanel"valign="top"align="left"height="100%" width="100%" x="0"y="0"backgroundColor="#4A4949" childLayout="absolute"visibleToMouse="true">
                    <panel id="r_tabspanel"valign="top"align="left"height="100%" width="100%" x="0"y="0"backgroundColor="#4A4949" childLayout="absolute"visibleToMouse="true"childClip="true">
                        <control id="r_tabs" name="tabGroup" buttonWidth="1" buttonHeight="1"x="0"y="0">
                            <control id="r_tab_1" name="tab" caption="Actions"x="0"y="0">
                                <panel id="r_tab_1_panel"valign="top"align="left"height="100%" width="100%" x="0"y="0"backgroundColor="#0000" childLayout="absolute"visibleToMouse="true">
                                    <control id="ridenametextfieldprefix"name="label" text="Change name:" x="0"y="10" color="ffffff"/>
                                    <control id="ridenametextfield"name="textfield" maxLength="50" x="96"y="10"height="22" width="200" />
                                    <control id="ridepricechangeprefix"name="label" text="Change price:" x="0"y="40" color="ffffff"/>
                                    <control id="ridepricechange"name="label" text="100.0" x="90"y="40" color="ffffff"/>
                                    <control id="ridepriceslider" max="20" name="horizontalSlider" stepSize="0.1" buttonStepSize="0.1" initial="2.0"width="160px" x="130"y="40"/>
                                    <image id="ridestatusbutton"filename="Interface/Rides/statusoff.png"x="340"y="0" childLayout="absolute" height="48"width="48"visibleToMouse="true">
                                        <interact onClick="rideStatusToggle()">
                                        </interact>
                                    </image>
                                    <control id="riderequestinspection" name="button" label="Request inspection" x="0"y="66"width="130"height="24"visibleToMouse="true">
                                        <interact onClick="rideRequestInspection()"/>
                                    </control>
                                    <control id="riderebuildenterance" name="button" label="Rebuild enterances" x="140"y="66"width="130"height="24"visibleToMouse="true">
                                        <interact onClick="rideRebuildEnterance()"/>
                                    </control>
                                    <control id="ridedemolishbutton" name="button" label="Demolish ride" x="280"y="66"width="130"height="24"visibleToMouse="true">
                                        <interact onClick="rideDemolishToggle()"/>
                                    </control>
                                </panel>
                            </control>
                            <control id="r_tab_2" name="tab" caption="Inspection"x="0"y="0">
                                <panel id="r_tab_2_panel"valign="top"align="left"height="100%" width="100%" x="0"y="0"backgroundColor="#0000" childLayout="absolute"visibleToMouse="true">
                                    <control id="ridelastinspectprefix"name="label" text="Last inspect: " x="0"y="10" color="#ffff"/>
                                    <control id="ridelastinspect"name="label" text="Not inspected " x="82"y="10" color="#ffff"/>
                                    <control id="rideworkingconditionsprefix"name="label" text="Working conditions: " x="0"y="30" color="#ffff"/>
                                    <control id="rideworkingconditions"name="label" text="Not inspected " x="130"y="30" color="#ffff"/>
                                    <control id="rideproductqualityprefix"name="label" text="Product quality: " x="0"y="50" color="#ffff"/>
                                    <control id="rideproductquality"name="label" text="Not inspected " x="102"y="50" color="#ffff"/>
                                    <control id="rideinspecttasteprefix"name="label" text="Left image: " x="0"y="70" color="#ffff"/>
                                    <control id="rideinspecttaste"name="label" text="Not inspected " x="72"y="70" color="#ffff"/>
                                    <control id="rideinspectedbyprefix"name="label" text="Inspected by: " x="0"y="90" color="#ffff"/>
                                    <control id="rideinspectedby"name="label" text="Not inspected" x="90"y="90" color="#ffff"/>
                                    <control id="rideinspectpaidprefix"name="label" text="Paid inspect: " x="0"y="110" color="#ffff"/>
                                    <control id="rideinspectpaid"name="label" text="Not inspected " x="82"y="110" color="#ffff"/>
                                    <control id="ridenotices"name="label" font="Interface/Fonts/Impact.fnt"text="Special notices" x="0"y="170" color="#FFF700"/>
                                    <control id="ridenoticeslistbox" name="listBox" vertical="off" width="450"height="100"horizontal="off" displayItems="7" selection="Single" x="0"y="190"/>
                                </panel>
                            </control>
                            <control id="r_tab_3" name="tab" caption="Information"x="0"y="0">
                                <panel id="tab_3_panel"valign="top"align="left"height="100%" width="100%" x="0"y="0"backgroundColor="#0000" childLayout="absolute"visibleToMouse="true">
                                    <control id="ridenameprefix"name="label" text="Name: " x="0"y="10" color="#ffff"/>
                                    <control id="ridename"name="label" text="temporaryname1 " x="42"y="10" color="#ffff"/>
                                    <control id="ridepriceprefix"name="label" text="Price: " x="0"y="30" color="#ffff"/>
                                    <control id="rideprice"name="label" text="100.0" x="40"y="30" color="#ffff"/>
                                    <control id="ridetypeprefix"name="label" text="Type: " x="0"y="50" color="#ffff"/>
                                    <control id="ridetype"name="label" text="Pirate Ship " x="40"y="50" color="#ffff"/>
                                    <control id="ridelocationprefix"name="label" text="Location: " x="0"y="70" color="#ffff"/>
                                    <control id="ridelocation"name="label" text="15X 6Y 15Z " x="60"y="70" color="#ffff"/>
                                    <control id="rideprofitbyprefix"name="label" text="Profit: " x="0"y="90" color="#ffff"/>
                                    <control id="rideprofit"name="label" text="1000.0 " x="40"y="90" color="#ffff"/>
                                    <control id="ridestatusprefix"name="label" text="Status: " x="0"y="110" color="#ffff"/>
                                    <control id="ridestatus"name="label" text="closed " x="50"y="110" color="#ffff"/>
                                    <control id="rideexcitementprefix"name="label" text="Excitement: " x="0"y="130" color="#ffff"/>
                                    <control id="rideexcitement"name="label" text="100 " x="76"y="130" color="#ffff"/>
                                    <control id="ridenauseaprefix"name="label" text="Nausea: " x="0"y="150" color="#ffff"/>
                                    <control id="ridenausea"name="label" text="100 " x="54"y="150" color="#ffff"/>
                                    <control id="ridebrokenprefix"name="label" text="Broken: " x="0"y="170" color="#ffff"/>
                                    <control id="ridebroken"name="label" text="100 " x="54"y="170" color="#ffff"/>
                                </panel>
                            </control>
                            <control id="r_tab_4" name="tab" caption="Feedback"x="0"y="0">
                                <panel id="tab_4_panel"valign="top"align="left"height="100%" width="100%" x="0"y="0"backgroundColor="#0000" childLayout="absolute"visibleToMouse="true">
                                    <control id="ridecustomersprefix"name="label" text="Customers: " x="0"y="10" color="#ffff"/>
                                    <control id="ridecustomers"name="label" text="9001 " x="78"y="10" color="#ffff"/>
                                    <control id="ridecustomersrideprefix"name="label" text="Customers in ride: " x="0"y="30" color="#ffff"/>
                                    <control id="ridecustomersride"name="label" text="22 " x="118"y="30" color="#ffff"/>
                                    <control id="ridecustomerfeedback"name="label" font="Interface/Fonts/Impact.fnt"text="Feedback" x="0"y="150" color="#FFF700"/>
                                    <control id="ridecustomerfeedbacklistbox" name="listBox" vertical="off" width="450"height="100"horizontal="off" displayItems="8" selection="Single" x="0"y="170"/>
                                </panel>
                            </control>
                        </control>
                    </panel>
                </panel>
            </control>
            <control id="NPCWindow" name="window"title="NPCS"width="400"height="560"x="200"y="200"hideOnClose="true"closeable="true"visibleToMouse="true">
                <panel id="n_rootpanel"valign="top"align="left"height="100%" width="100%" backgroundColor="#999f" childLayout="absolute"visibleToMouse="true"x="0"y="0">
                    <control id="guests" name="dropDown"x="40"y="10"displayItems="20" align="left" valign="top"visibleToMouse="true"height="23" width="300"/>
                </panel>
            </control>
            <control id="inspectionWindow" name="window"title="Request an inspection"width="200"height="150"x="400"y="200"hideOnClose="true"closeable="true">
                <panel id="inspectionpanel"valign="top"align="left"height="100%" width="100%" backgroundColor="#555f" childLayout="absolute"visibleToMouse="true">
                    <control id="inspectiontoprefix"name="label" text="Request inspection to:" x="4"y="0" color="#ffff"/>
                    <control id="inspectionto"name="label" text="Haunting House 1222121" x="4"y="22" color="#ffff"/>
                    <control id="inspectionpayprefix"name="label" text="Pay under the desk" x="4"y="44" color="#ffff"/>
                    <control id="inspectionpaycheckbox" name="checkbox" x="130"y="44"/>
                    <control id="inspectionpaytext"name="label" text="Amount:" x="4"y="70" color="#ffff"/>
                    <control id="inspectionpay"name="label" text="1000" x="74"y="70" color="#ffff"/>
                    <control id="inspectionaddvalue" name="button" label="+$" x="120"y="70"width="20"height="24"visibleToMouse="true">
                        <interact onClick="inspectionAddValue()"/>
                    </control>
                    <control id="inspectiontakevalue" name="button" label="-$" x="142"y="70"width="20"height="24"visibleToMouse="true">
                        <interact onClick="inspectionTakeValue()"/>
                    </control>
                    <control id="inspectionrequest" name="button" label="Request" x="14"y="100"width="80"height="24"visibleToMouse="true">
                        <interact onClick="inspectionRequest()"/>
                    </control>
                    <control id="inspectioncancel" name="button" label="Cancel" x="100"y="100"width="80"height="24"visibleToMouse="true">
                        <interact onClick="resetUI()"/>
                    </control>
                </panel>
            </control>
            <control id="decorationWindow" name="window"title="DECORATIONS"width="800"height="400"x="200"y="200"hideOnClose="true"closeable="false">
                <panel x="0"y="0"id="decorationtaustapanel"valign="top"align="left"height="100%" width="100%" backgroundColor="#000000" childLayout="absolute"visibleToMouse="true">
                    <panel x="0"y="0"id="decorationuppanel"valign="top"align="left"height="120" width="100%" backgroundColor="#808080" childLayout="absolute"visibleToMouse="true"childClip="false">
                        <image id="decorationdirectionimg"filename="Interface/Roads/right.png"x="48"y="10" childLayout="absolute" height="64"width="64"visibleToMouse="true">

                        </image>
                        <image filename="Interface/Decoration/left.png"x="30"y="76" childLayout="absolute" height="48"width="48"visibleToMouse="true">
                            <interact onClick="turnDecorationLeft()">
                            </interact>
                        </image>
                        <image filename="Interface/Decoration/right.png"x="78"y="76" childLayout="absolute" height="48"width="48"visibleToMouse="true">
                            <interact onClick="turnDecorationRight()">
                            </interact>
                        </image>
                        <image filename="Interface/Decoration/rock.png"x="380"y="26" childLayout="absolute" height="72"width="72"visibleToMouse="true">
                            <interact onClick="">
                            </interact>
                        </image>
                        <panel x="500"y="10"id="decoration123114123"valign="top"align="left"height="100" width="280" backgroundColor="#BFAD77" childLayout="absolute"visibleToMouse="true"wrap="true">
                            <control id="decorationname"name="label" text="DefaultName" x="10"y="0" color="ffffff"/>
                            <control id="decorationdescription"name="label" text="deded00000000000000000000000000" x="10"y="40" color="ffffff"/>
                        </panel>
                    </panel>
                    <panel x="0"y="120"id="decorationdownpanel"valign="top"align="left"height="250" width="100%" backgroundColor="#ffffff" childLayout="absolute"visibleToMouse="true"childClip="true">
                        <control id="decorationscrollbar" name="scrollPanel" horizontal="false" height="240" x="30"y="0"pageSizeY="4"stepSizeY="2"childClip="false">
                            <panel id="dscrollpanel"valign="top"align="left"height="600" width="740" backgroundColor="#FFF0D1" childLayout="absolute"visibleToMouse="true"x="0"y="0">
                                <image filename="Interface/Decoration/rock.png"x="10"y="20" childLayout="absolute" height="64"width="64"visibleToMouse="true">
                                    <interact onClick="selectRock()">
                                    </interact>
                                </image>
                                <image filename="Interface/Shops/Nopic.png"x="79"y="20" childLayout="absolute" height="64"width="64"visibleToMouse="true">
                                    <interact onClick="">
                                    </interact>
                                </image>
                                <image filename="Interface/Shops/Nopic.png"x="148"y="20" childLayout="absolute" height="64"width="64"visibleToMouse="true">
                                    <interact onClick="">
                                    </interact>
                                </image>
                                <image filename="Interface/Shops/Nopic.png"x="217"y="20" childLayout="absolute" height="64"width="64"visibleToMouse="true">
                                    <interact onClick="">
                                    </interact>
                                </image>
                                <image filename="Interface/Shops/Nopic.png"x="286"y="20" childLayout="absolute" height="64"width="64"visibleToMouse="true">
                                    <interact onClick="">
                                    </interact>
                                </image>
                                <image filename="Interface/Shops/Nopic.png"x="355"y="20" childLayout="absolute" height="64"width="64"visibleToMouse="true">
                                    <interact onClick="">
                                    </interact>
                                </image>
                                <image filename="Interface/Shops/Nopic.png"x="424"y="20" childLayout="absolute" height="64"width="64"visibleToMouse="true">
                                    <interact onClick="">
                                    </interact>
                                </image>
                                <image filename="Interface/Shops/Nopic.png"x="493"y="20" childLayout="absolute" height="64"width="64"visibleToMouse="true">
                                    <interact onClick="">
                                    </interact>
                                </image>
                                <image filename="Interface/Shops/Nopic.png"x="562"y="20" childLayout="absolute" height="64"width="64"visibleToMouse="true">
                                    <interact onClick="">
                                    </interact>
                                </image>
                                <image filename="Interface/Shops/Nopic.png"x="631"y="20" childLayout="absolute" height="64"width="64"visibleToMouse="true">
                                    <interact onClick="">
                                    </interact>
                                </image>

                                <image filename="Interface/Shops/Nopic.png"x="10"y="89" childLayout="absolute" height="64"width="64"visibleToMouse="true">
                                    <interact onClick="">
                                    </interact>
                                </image>
                                <image filename="Interface/Shops/Nopic.png"x="79"y="89" childLayout="absolute" height="64"width="64"visibleToMouse="true">
                                    <interact onClick="">
                                    </interact>
                                </image>
                            </panel>
                        </control>
                    </panel>
                </panel>
            </control>
        </layer>
    </screen>
</nifty>
